MANIFEST.in
readme.md
setup.py
easydb/__init__.py
easydb.egg-info/PKG-INFO
easydb.egg-info/SOURCES.txt
easydb.egg-info/dependency_links.txt
easydb.egg-info/not-zip-safe
easydb.egg-info/top_level.txt