Metadata-Version: 1.0
Name: easydb
Version: 0.2
Summary: Simple SQLite wrapper to make it easier to manage your database
Home-page: https://github.com/coderholic/easydb
Author: Ben Dowling
Author-email: ben.m.dowling@gmail.com
License: MIT
Keywords: db database sqlite
Platform: UNKNOWN
